LICENSE.rst
MANIFEST.in
README.md
requirements.txt
setup.py
src/__init__.py
src/manage.py
src/tipboard/__init__.py
src/tipboard/app/__init__.py
src/tipboard/app/applicationconfig.py
src/tipboard/app/cache.py
src/tipboard/app/flipboard.py
src/tipboard/app/parser.py
src/tipboard/app/properties.py
src/tipboard/app/routing.py
src/tipboard/app/utils.py
src/tipboard/app/Config/layout_config.yaml
src/tipboard/app/Config/properties.json
src/tipboard/app/extras/__init__.py
src/tipboard/app/extras/client_code_example.py
src/tipboard/app/extras/fabfile.py
src/tipboard/app/extras/jira-ds.py
src/tipboard/app/views/__init__.py
src/tipboard/app/views/api.py
src/tipboard/app/views/dashboard.py
src/tipboard/app/views/wshandler.py
src/tipboard/static/css/jquery.jqplot.css
src/tipboard/static/css/layout.css
src/tipboard/static/css/reset.css
src/tipboard/static/fonts/MISO_LICENSE
src/tipboard/static/fonts/miso-light-webfont.eot
src/tipboard/static/fonts/miso-light-webfont.svg
src/tipboard/static/fonts/miso-light-webfont.ttf
src/tipboard/static/fonts/miso-light-webfont.woff
src/tipboard/static/fonts/miso-webfont.eot
src/tipboard/static/fonts/miso-webfont.svg
src/tipboard/static/fonts/miso-webfont.ttf
src/tipboard/static/fonts/miso-webfont.woff
src/tipboard/static/js/flipboard.js
src/tipboard/static/js/tipboard.js
src/tipboard/static/js/lib/html5shiv.js
src/tipboard/static/js/lib/jquery.fullscreen.js
src/tipboard/static/js/lib/jquery.js
src/tipboard/static/js/lib/require.js
src/tipboard/static/js/lib/simplify.js
src/tipboard/static/js/lib/jqplot/excanvas.min.js
src/tipboard/static/js/lib/jqplot/jquery.jqplot.js
src/tipboard/static/js/lib/jqplot/plugins/jqplot.BezierCurveRenderer.js
src/tipboard/static/js/lib/jqplot/plugins/jqplot.barRenderer.js
src/tipboard/static/js/lib/jqplot/plugins/jqplot.blockRenderer.js
src/tipboard/static/js/lib/jqplot/plugins/jqplot.bubbleRenderer.js
src/tipboard/static/js/lib/jqplot/plugins/jqplot.canvasAxisLabelRenderer.js
tipboard2.0.egg-info/PKG-INFO
tipboard2.0.egg-info/SOURCES.txt
tipboard2.0.egg-info/dependency_links.txt
tipboard2.0.egg-info/entry_points.txt
tipboard2.0.egg-info/requires.txt
tipboard2.0.egg-info/top_level.txt