Metadata-Version: 2.1
Name: tipboard2.0
Version: 1.0.5
Summary: Tipboard - a flexible solution for creating your dashboards.
Home-page: http://tipboard.allegrogroup.com
Author: Allegro Group and Contributors
Author-email: pylabs@allegro.pl
License: Apache Software License v2.0
Platform: UNKNOWN
